quantchdb/__init__.py
quantchdb/chdb_commands.py
quantchdb/set_logging.py
quantchdb/utils.py
quantchdb-0.2.0.dist-info/licenses/LICENSE.txt
quantchdb-0.2.0.dist-info/METADATA
quantchdb-0.2.0.dist-info/WHEEL
quantchdb-0.2.0.dist-info/top_level.txt
quantchdb-0.2.0.dist-info/RECORD
