Metadata-Version: 2.4
Name: quantchdb
Version: 0.2.0
Summary: A Well-Encapsulated ClickHouse Database APIs Lib
Home-page: https://github.com/ElenYoung/chdb
Author: Young
Author-email: yang13515360252@163.com
Classifier: Programming Language :: Python :: 3
Classifier: License :: OSI Approved :: MIT License
Classifier: Operating System :: OS Independent
Requires-Python: >=3.8
License-File: LICENSE.txt
Requires-Dist: numpy>=2
Requires-Dist: clickhouse-driver>=0.2.9
Requires-Dist: pandas>=2
Requires-Dist: pytz>=2025.2
Requires-Dist: coloredlogs>=15.0.1
Requires-Dist: python-dotenv>=1.1.1
Dynamic: author
Dynamic: author-email
Dynamic: classifier
Dynamic: description
Dynamic: description-content-type
Dynamic: home-page
Dynamic: license-file
Dynamic: requires-dist
Dynamic: requires-python
Dynamic: summary
